ccorp/ruamel/yaml/include/__init__.py
ccorp_yaml_include_relative_path-0.0.4.dist-info/METADATA
ccorp_yaml_include_relative_path-0.0.4.dist-info/RECORD
ccorp_yaml_include_relative_path-0.0.4.dist-info/WHEEL
ccorp_yaml_include_relative_path-0.0.4.dist-info/top_level.txt
