Metadata-Version: 2.1
Name: ccorp-yaml-include-relative-path
Version: 0.0.4
Summary: Exactly ccorp-yaml-include package with a bug fix and support of relative paths for included aliases
Home-page: https://github.com/marsoloGit/ccorp_yaml_include
Author: Marina Lalazarova
Author-email: marsolo@mail.ru
License: UNKNOWN
Platform: UNKNOWN
Classifier: Programming Language :: Python :: 3
Classifier: License :: OSI Approved :: MIT License
Classifier: Operating System :: OS Independent
Requires-Dist: ruamel.yaml
